Metadata-Version: 2.1
Name: ctmc2
Version: 0.1.0
Summary: Continous Time Markov Chain (with automatic error correction)
Home-page: http://github.com/kmedian/ctmc2
Author: Ulf Hamster
Author-email: 554c46@gmail.com
License: MIT
Platform: UNKNOWN
Requires-Python: >=3.6
